SISLab/__init__.py
SISLab/utils/__init__.py
SISLab/utils/concurrent_processor.py
SISLab/utils/loader.py
SISLab/utils/proccessor/__init__.py
SISLab/utils/proccessor/image.py
SISLab-0.0.0.post17.dist-info/LICENSE
SISLab-0.0.0.post17.dist-info/METADATA
SISLab-0.0.0.post17.dist-info/WHEEL
SISLab-0.0.0.post17.dist-info/top_level.txt
SISLab-0.0.0.post17.dist-info/RECORD
